nendo_plugin_classify_core/__init__.py
nendo_plugin_classify_core/config.py
nendo_plugin_classify_core/plugin.py
nendo_plugin_classify_core/utils.py
nendo_plugin_classify_core-0.2.11.dist-info/LICENSE
nendo_plugin_classify_core-0.2.11.dist-info/METADATA
nendo_plugin_classify_core-0.2.11.dist-info/WHEEL
nendo_plugin_classify_core-0.2.11.dist-info/RECORD
