Metadata-Version: 2.1
Name: nendo-plugin-classify-core
Version: 0.2.11
Summary: Nendo plugin for automatic music information retrieval.
Home-page: https://okio.ai
License: MIT
Keywords: Nendo,Plugin,Audio,Generative,Music,Audio Production,Audio Analysis
Author: Felix Lorenz
Author-email: felix@okio.ai
Requires-Python: >=3.8,<3.11
Classifier: Development Status :: 5 - Production/Stable
Classifier: Intended Audience :: Developers
Classifier: License :: OSI Approved :: MIT License
Classifier: Operating System :: OS Independent
Classifier: Programming Language :: Python :: 3
Classifier: Programming Language :: Python :: 3.8
Classifier: Programming Language :: Python :: 3.9
Classifier: Programming Language :: Python :: 3.10
Classifier: Topic :: Multimedia :: Sound/Audio
Requires-Dist: essentia-tensorflow (>=2.1b6.dev1110,<3.0)
Requires-Dist: nendo (>=0.2.3,<0.3.0)
Requires-Dist: pydantic (>=2.0.0,<2.5.0)
Requires-Dist: tqdm (>=4.65.0,<5.0.0)
Project-URL: Repository, https://github.com/okio-ai/nendo_plugin_classify_core
